satyrn_python/__init__.py
satyrn_python/app.py
satyrn_python/asciiart.txt
satyrn_python/entry_point.py
satyrn_python/interpreter.py
satyrn_python/__pycache__/__init__.cpython-37.pyc
satyrn_python/__pycache__/app.cpython-37.pyc
satyrn_python/__pycache__/entry_point.cpython-37.pyc
satyrn_python/__pycache__/interpreter.cpython-37.pyc
satyrn_python/static/cover.png
satyrn_python/static/icon.png
satyrn_python/static/codemirror/.editorconfig
satyrn_python/static/codemirror/.gitattributes
satyrn_python/static/codemirror/.npmignore
satyrn_python/static/codemirror/.travis.yml
satyrn_python/static/codemirror/AUTHORS
satyrn_python/static/codemirror/CHANGELOG.md
satyrn_python/static/codemirror/CONTRIBUTING.md
satyrn_python/static/codemirror/LICENSE
satyrn_python/static/codemirror/README.md
satyrn_python/static/codemirror/index.html
satyrn_python/static/codemirror/package.json
satyrn_python/static/codemirror/rollup.config.js
satyrn_python/static/codemirror/addon/comment/comment.js
satyrn_python/static/codemirror/addon/comment/continuecomment.js
satyrn_python/static/codemirror/addon/dialog/dialog.css
satyrn_python/static/codemirror/addon/dialog/dialog.js
satyrn_python/static/codemirror/addon/display/autorefresh.js
satyrn_python/static/codemirror/addon/display/fullscreen.css
satyrn_python/static/codemirror/addon/display/fullscreen.js
satyrn_python/static/codemirror/addon/display/panel.js
satyrn_python/static/codemirror/addon/display/placeholder.js
satyrn_python/static/codemirror/addon/display/rulers.js
satyrn_python/static/codemirror/addon/edit/closebrackets.js
satyrn_python/static/codemirror/addon/edit/closetag.js
satyrn_python/static/codemirror/addon/edit/continuelist.js
satyrn_python/static/codemirror/addon/edit/matchbrackets.js
satyrn_python/static/codemirror/addon/edit/matchtags.js
satyrn_python/static/codemirror/addon/edit/trailingspace.js
satyrn_python/static/codemirror/addon/fold/brace-fold.js
satyrn_python/static/codemirror/addon/fold/comment-fold.js
satyrn_python-0.10.2.dist-info/LICENSE
satyrn_python-0.10.2.dist-info/METADATA
satyrn_python-0.10.2.dist-info/WHEEL
satyrn_python-0.10.2.dist-info/entry_points.txt
satyrn_python-0.10.2.dist-info/top_level.txt
satyrn_python-0.10.2.dist-info/RECORD
