Metadata-Version: 2.1
Name: satyrn-python
Version: 0.10.2
Summary: A Notebook alternative that supports branching code
Home-page: https://github.com/CharlesAverill/satyrn/
Author: Charles Averill
Author-email: charlesaverill20@gmail.com
License: UNKNOWN
Project-URL: Documentation, https://satyrn.readthedocs.io/
Platform: UNKNOWN
Classifier: Programming Language :: Python :: 3
Classifier: License :: OSI Approved :: MIT License
Classifier: Operating System :: OS Independent
Requires-Dist: networkx
Requires-Dist: matplotlib
Requires-Dist: flask
Requires-Dist: cherrypy
Requires-Dist: nbformat
Requires-Dist: beautifulsoup4
